.DS_Store
fa_py/__init__.py
fa_py-0.2.dist-info/DESCRIPTION.rst
fa_py-0.2.dist-info/METADATA
fa_py-0.2.dist-info/RECORD
fa_py-0.2.dist-info/WHEEL
fa_py-0.2.dist-info/metadata.json
fa_py-0.2.dist-info/top_level.txt
